citrailmu/__init__.py
citrailmu/webui.py
citrailmu-25.3.8.dist-info/licenses/LICENSE
citrailmu-25.3.8.dist-info/METADATA
citrailmu-25.3.8.dist-info/WHEEL
citrailmu-25.3.8.dist-info/top_level.txt
citrailmu-25.3.8.dist-info/RECORD
