Metadata-Version: 2.4
Name: citrailmu
Version: 25.3.8
Summary: Convert lectures/talks from video/audio/YouTube into text (#GodamSahur 2025)
Author-email: ikmalsaid <ikmalsaid@gmail.com>
Project-URL: Homepage, https://github.com/ikmalsaid/citrailmu
Project-URL: Issues, https://github.com/ikmalsaid/citrailmu/issues
Classifier: Programming Language :: Python :: 3
Classifier: Topic :: Scientific/Engineering :: Artificial Intelligence
Classifier: License :: OSI Approved :: GNU Affero General Public License v3
Classifier: Operating System :: OS Independent
Requires-Python: >=3.8
License-File: LICENSE
Requires-Dist: google-generativeai
Requires-Dist: colorpaws
Requires-Dist: gradio==4.38.1
Requires-Dist: fastapi==0.112.4
Requires-Dist: pydantic==2.10.6
Requires-Dist: pytubefix
Requires-Dist: moviepy==1.0.3
Requires-Dist: markdown-pdf
Dynamic: license-file
